mixrpay_merchant/__init__.py
mixrpay_merchant/charges.py
mixrpay_merchant/flask.py
mixrpay_merchant/middleware.py
mixrpay_merchant/receipt.py
mixrpay_merchant/types.py
mixrpay_merchant/verify.py
mixrpay_merchant-0.2.0.dist-info/METADATA
mixrpay_merchant-0.2.0.dist-info/WHEEL
mixrpay_merchant-0.2.0.dist-info/RECORD
