Metadata-Version: 2.4
Name: mixrpay-merchant
Version: 0.2.0
Summary: Add x402 payments to your Python API - FastAPI and Flask middleware
Project-URL: Homepage, https://github.com/mixrpay/merchant-sdk-python
Project-URL: Documentation, https://docs.mixrpay.com/merchant-sdk/python
Project-URL: Repository, https://github.com/mixrpay/merchant-sdk-python
Author-email: MixrPay <support@mixrpay.com>
License: MIT
Keywords: agents,ai,crypto,fastapi,flask,micropayments,middleware,payments,usdc,x402
Classifier: Development Status :: 4 - Beta
Classifier: Framework :: FastAPI
Classifier: Framework :: Flask
Classifier: Intended Audience :: Developers
Classifier: License :: OSI Approved :: MIT License
Classifier: Programming Language :: Python :: 3
Classifier: Programming Language :: Python :: 3.9
Classifier: Programming Language :: Python :: 3.10
Classifier: Programming Language :: Python :: 3.11
Classifier: Programming Language :: Python :: 3.12
Classifier: Topic :: Internet :: WWW/HTTP :: HTTP Servers
Requires-Python: >=3.9
Requires-Dist: eth-account>=0.10.0
Requires-Dist: eth-typing>=3.0.0
Requires-Dist: httpx>=0.25.0
Requires-Dist: pyjwt>=2.8.0
Provides-Extra: all
Requires-Dist: fastapi>=0.100.0; extra == 'all'
Requires-Dist: flask>=2.0.0; extra == 'all'
Requires-Dist: starlette>=0.27.0; extra == 'all'
Provides-Extra: dev
Requires-Dist: fastapi>=0.100.0; extra == 'dev'
Requires-Dist: flask>=2.0.0; extra == 'dev'
Requires-Dist: httpx>=0.25.0; extra == 'dev'
Requires-Dist: pytest-asyncio>=0.21.0; extra == 'dev'
Requires-Dist: pytest>=7.0.0; extra == 'dev'
Requires-Dist: uvicorn>=0.23.0; extra == 'dev'
Provides-Extra: fastapi
Requires-Dist: fastapi>=0.100.0; extra == 'fastapi'
Requires-Dist: starlette>=0.27.0; extra == 'fastapi'
Provides-Extra: flask
Requires-Dist: flask>=2.0.0; extra == 'flask'
